{
    "transform2D": {
        "position": {
            "x": 0,
            "y": 0
        },
        "scale": {
            "x": 1,
            "y": 1
        },
        "anchor": {
            "x": 0,
            "y": 0.5
        },
        "size": {
            "x": 200,
            "y": 200
        },
        "rotation": 0,
        "transform": true
    },
    "container": {},
    "group": {
        "id": "dialogues"
    },
    "sprite": {
        "animations": {
        }
    },
    "bitmaptext": {
        "position": {
            "x": 0,
            "y": 0
        },
        "text": "default",
        "color": "0xFFFFFF",
        "fontFamily": "Kanit",
        "fontSize":30,
        "align": "center",
        "anchor": 0.5
    }
}